build-scripts
dist
pylint_mongoengine
