Metadata-Version: 2.1
Name: pylint-mongoengine
Version: 0.6.0
Summary: A Pylint plugin to help it understand MongoEngine
Author: Juca Crispim
Classifier: Development Status :: 4 - Beta
Classifier: Environment :: Console
Classifier: Intended Audience :: Developers
Classifier: Operating System :: Unix
Classifier: Topic :: Software Development :: Quality Assurance
Classifier: Programming Language :: Python :: 3
License-File: LICENSE
Requires-Dist: pylint>=3.2.0
Requires-Dist: pylint-plugin-utils>=0.8.2
